LICENSE
README.md
setup.py
strath/__init__.py
strath/strath.py
strath.egg-info/PKG-INFO
strath.egg-info/SOURCES.txt
strath.egg-info/dependency_links.txt
strath.egg-info/top_level.txt
tests/test_strath.py