Metadata-Version: 2.2
Name: strath
Version: 1.0.3
Summary: This library helps ensuring that a file path is of type str or pathlib.Path.
Home-page: https://github.com/GRV96/strath
Author: Guyllaume Rousseau
License: MIT
Classifier: Development Status :: 5 - Production/Stable
Classifier: Intended Audience :: Developers
Classifier: License :: OSI Approved :: MIT License
Classifier: Operating System :: OS Independent
Classifier: Programming Language :: Python :: 3.6
Classifier: Topic :: Utilities
License-File: LICENSE
Dynamic: author
Dynamic: classifier
Dynamic: description
Dynamic: description-content-type
Dynamic: home-page
Dynamic: license
Dynamic: summary
